telcell/__init__.py
telcell/cell_identity.py
telcell/pipeline.py
telcell/auxilliary_models/__init__.py
telcell/auxilliary_models/antenna.py
telcell/auxilliary_models/extended_geography.py
telcell/auxilliary_models/geography.py
telcell/auxilliary_models/rare_pair/__init__.py
telcell/auxilliary_models/rare_pair/corrected_priors.py
telcell/auxilliary_models/rare_pair/coverage_model.py
telcell/auxilliary_models/rare_pair/features.py
telcell/auxilliary_models/rare_pair/predictor.py
telcell/auxilliary_models/rare_pair/transformers.py
telcell/auxilliary_models/rare_pair/utils.py
telcell/auxilliary_models/rare_pair/validation.py
telcell/models/__init__.py
telcell/models/dummy.py
telcell/models/model.py
telcell/models/rare_pair_feature_based.py
telcell/models/simplemodel.py
tests/__init__.py
tests/conftest.py
tests/make_test_data.py
tests/make_test_measurements.py
tests/test_cell_identity.py
telcell-0.0.2.dist-info/METADATA
telcell-0.0.2.dist-info/WHEEL
telcell-0.0.2.dist-info/top_level.txt
telcell-0.0.2.dist-info/RECORD
