Metadata-Version: 2.1
Name: telcell
Version: 0.0.2
Summary: Calculating LRs for Collocated Tracks
Author: Netherlands Forensics Institute
Requires-Dist: lir
Requires-Dist: lrbenchmark >=0.1.1
Requires-Dist: numpy
